LICENSE
MANIFEST.in
README.md
main.py
setup.py
codeplateau.egg-info/PKG-INFO
codeplateau.egg-info/SOURCES.txt
codeplateau.egg-info/dependency_links.txt
codeplateau.egg-info/entry_points.txt
codeplateau.egg-info/requires.txt
codeplateau.egg-info/top_level.txt
scripts/__init__.py
scripts/egg.py
scripts/pen.py
scripts/socail.py