Metadata-Version: 2.1
Name: codeplateau
Version: 1.0.7
Summary: CLI tool that makes coding easy and fun.
Home-page: https://github.com/jonathan-felicity/codepleateau.git
Author: Jonathan Felicity
Author-email: jonathanfelicity@mail.com
License: UNKNOWN
Platform: UNKNOWN
Requires-Python: >=3.7
License-File: LICENSE
